fisher/__init__.py
fisher/src/asa159.c
fisher/src/fisher.c
tests/__init__.py
tests/test_rpy2.py
fisher_test_python-0.2.2.dist-info/LICENSE
fisher_test_python-0.2.2.dist-info/METADATA
fisher_test_python-0.2.2.dist-info/WHEEL
fisher_test_python-0.2.2.dist-info/top_level.txt
fisher_test_python-0.2.2.dist-info/RECORD
