Metadata-Version: 2.1
Name: fisher-test-python
Version: 0.2.2
Summary: Fisher exact test for python
Home-page: https://github.com/linewalks/fisher-test-python
Author: Linewalks
Author-email: jungwoo@linewalks.com
License: LGPL-3.0
Platform: UNKNOWN
Requires-Python: >=3.6
License-File: LICENSE
Requires-Dist: numpy
Requires-Dist: scipy
